Workbook

Sheet data
A1: Date | B1: Drink | C1: Category | D1: Quantity | E1: Cost per Unit | F1: Price | G1: Salesperson | H1: Store Location | I1: Revenue | J1: Sales level | K1: Bouns rate
A2: 46236 | B2: Cappuccino | C2: Cold Coffee | D2: 4 | E2: 27 | F2: 120 | G2: Omar | H2: Dokki | I2: =Table1[[#This Row],[Quantity ]]*Table1[[#This Row],[Price ]] -> 480 | J2: =IF(Table1[[#This Row],[Revenue]]>600,"High","Normal") -> Normal | K2: =_xlfn.XLOOKUP(Table1[[#This Row],[Salesperson]],Bouns!$A$2:$A$5,Bouns!$B$2:$B$5, "Not Found") -> Not Found
A3: 45921 | B3: Mocha | C3: Cold Coffee | D3: 6 | E3: 42 | F3: 118 | G3: Sara | H3: Heliopolis | I3: =Table1[[#This Row],[Quantity ]]*Table1[[#This Row],[Price ]] -> 708 | J3: =IF(Table1[[#This Row],[Revenue]]>600,"High","Normal") -> High | K3: =_xlfn.XLOOKUP(Table1[[#This Row],[Salesperson]],Bouns!$A$2:$A$5,Bouns!$B$2:$B$5, "Not Found") -> 0.04
A4: 45885 | B4: Iced Coffee | C4: Cold Coffee | D4: 1 | E4: 49 | F4: 118 | G4: Khaled | H4: Zamalek | I4: =Table1[[#This Row],[Quantity ]]*Table1[[#This Row],[Price ]] -> 118 | J4: =IF(Table1[[#This Row],[Revenue]]>600,"High","Normal") -> Normal | K4: =_xlfn.XLOOKUP(Table1[[#This Row],[Salesperson]],Bouns!$A$2:$A$5,Bouns!$B$2:$B$5, "Not Found") -> 0.05
A5: 46007 | B5: Mocha | C5: Cold Coffee | D5: 8 | E5: 21 | F5: 116 | G5: Omar | H5: Dokki | I5: =Table1[[#This Row],[Quantity ]]*Table1[[#This Row],[Price ]] -> 928 | J5: =IF(Table1[[#This Row],[Revenue]]>600,"High","Normal") -> High | K5: =_xlfn.XLOOKUP(Table1[[#This Row],[Salesperson]],Bouns!$A$2:$A$5,Bouns!$B$2:$B$5, "Not Found") -> Not Found
A6: 45754 | B6: Cappuccino | C6: Cold Coffee | D6: 9 | E6: 49 | F6: 114 | G6: Sara | H6: Dokki | I6: =Table1[[#This Row],[Quantity ]]*Table1[[#This Row],[Price ]] -> 1026 | J6: =IF(Table1[[#This Row],[Revenue]]>600,"High","Normal") -> High | K6: =_xlfn.XLOOKUP(Table1[[#This Row],[Salesperson]],Bouns!$A$2:$A$5,Bouns!$B$2:$B$5, "Not Found") -> 0.04
A7: 45847 | B7: Cappuccino | C7: Hot Coffee | D7: 6 | E7: 50 | F7: 113 | G7: Sara | H7: Dokki | I7: =Table1[[#This Row],[Quantity ]]*Table1[[#This Row],[Price ]] -> 678 | J7: =IF(Table1[[#This Row],[Revenue]]>600,"High","Normal") -> High | K7: =_xlfn.XLOOKUP(Table1[[#This Row],[Salesperson]],Bouns!$A$2:$A$5,Bouns!$B$2:$B$5, "Not Found") -> 0.04
A8: 45982 | B8: Latte | C8: Hot Coffee | D8: 6 | E8: 37 | F8: 113 | G8: Omar | H8: Heliopolis | I8: =Table1[[#This Row],[Quantity ]]*Table1[[#This Row],[Price ]] -> 678 | J8: =IF(Table1[[#This Row],[Revenue]]>600,"High","Normal") -> High | K8: =_xlfn.XLOOKUP(Table1[[#This Row],[Salesperson]],Bouns!$A$2:$A$5,Bouns!$B$2:$B$5, "Not Found") -> Not Found
A9: 45981 | B9: Iced Coffee | C9: Special Drinks | D9: 4 | E9: 48 | F9: 112 | G9: Omar | H9: Maadi | I9: =Table1[[#This Row],[Quantity ]]*Table1[[#This Row],[Price ]] -> 448 | J9: =IF(Table1[[#This Row],[Revenue]]>600,"High","Normal") -> Normal | K9: =_xlfn.XLOOKUP(Table1[[#This Row],[Salesperson]],Bouns!$A$2:$A$5,Bouns!$B$2:$B$5, "Not Found") -> Not Found
A10: 45956 | B10: Espresso | C10: Cold Coffee | D10: 1 | E10: 33 | F10: 110 | G10: Khaled | H10: Dokki | I10: =Table1[[#This Row],[Quantity ]]*Table1[[#This Row],[Price ]] -> 110 | J10: =IF(Table1[[#This Row],[Revenue]]>600,"High","Normal") -> Normal | K10: =_xlfn.XLOOKUP(Table1[[#This Row],[Salesperson]],Bouns!$A$2:$A$5,Bouns!$B$2:$B$5, "Not Found") -> 0.05
A11: 45785 | B11: Espresso | C11: Hot Coffee | D11: 5 | E11: 23 | F11: 109 | G11: Khaled | H11: Heliopolis | I11: =Table1[[#This Row],[Quantity ]]*Table1[[#This Row],[Price ]] -> 545 | J11: =IF(Table1[[#This Row],[Revenue]]>600,"High","Normal") -> Normal | K11: =_xlfn.XLOOKUP(Table1[[#This Row],[Salesperson]],Bouns!$A$2:$A$5,Bouns!$B$2:$B$5, "Not Found") -> 0.05
A12: 45776 | B12: Mocha | C12: Hot Coffee | D12: 1 | E12: 42 | F12: 109 | G12: Sara | H12: Heliopolis | I12: =Table1[[#This Row],[Quantity ]]*Table1[[#This Row],[Price ]] -> 109 | J12: =IF(Table1[[#This Row],[Revenue]]>600,"High","Normal") -> Normal | K12: =_xlfn.XLOOKUP(Table1[[#This Row],[Salesperson]],Bouns!$A$2:$A$5,Bouns!$B$2:$B$5, "Not Found") -> 0.04
A13: 45857 | B13: Espresso | C13: Cold Coffee | D13: 9 | E13: 49 | F13: 108 | G13: Ahmed | H13: Zamalek | I13: =Table1[[#This Row],[Quantity ]]*Table1[[#This Row],[Price ]] -> 972 | J13: =IF(Table1[[#This Row],[Revenue]]>600,"High","Normal") -> High | K13: =_xlfn.XLOOKUP(Table1[[#This Row],[Salesperson]],Bouns!$A$2:$A$5,Bouns!$B$2:$B$5, "Not Found") -> 0.05
... A51: 45879 | B51: Mocha | C51: Special Drinks | D51: 3 | E51: 32 | F51: 60 | G51: Mona | H51: Maadi | I51: =Table1[[#This Row],[Quantity ]]*Table1[[#This Row],[Price ]] -> 180 | J51: =IF(Table1[[#This Row],[Revenue]]>600,"High","Normal") -> Normal | K51: =_xlfn.XLOOKUP(Table1[[#This Row],[Salesperson]],Bouns!$A$2:$A$5,Bouns!$B$2:$B$5, "Not Found") -> 0.06

Sheet Bouns
A1: Salesperson | B1: Bonus Rate
A2: Ahmed | B2: 0.05
A3: Mona | B3: 0.06
A4: Sara | B4: 0.04
A5: Khaled | B5: 0.05

Sheet Pivot table1
B1: Sales Person
B2: Ahmed | D2: Khaled | F2: Mona | H2: Omar | J2: Sara
A3: Sales Location | B3: Sum of Revenue | C3: Sum of Bouns Amount | D3: Sum of Revenue | E3: Sum of Bouns Amount | F3: Sum of Revenue | G3: Sum of Bouns Amount | H3: Sum of Revenue | I3: Sum of Bouns Amount | J3: Sum of Revenue | K3: Sum of Bouns Amount
A4: Dokki | B4: 930 | C4: 46.5 | D4: 110 | E4: 5.5 | F4: 1219 | G4: 219.42 | H4: 2002 | I4: 0 | J4: 2568 | K4: 410.88
A5: Heliopolis | B5: 1190 | C5: 119 | D5: 2314 | E5: 462.8 | F5: 966 | G5: 115.92 | H5: 678 | I5: 0 | J5: 1024 | K5: 122.88
A6: Maadi | B6: 644 | C6: 32.2 | D6: 147 | E6: 14.7 | F6: 1125 | G6: 202.5 | H6: 938 | I6: 0 | J6: 2037 | K6: 407.4
A7: Zamalek | B7: 2666 | C7: 533.2 | D7: 118 | E7: 5.9 | F7: 1855 | G7: 333.9 | H7: 651 | I7: 0 | J7: 1809 | K7: 289.44

Sheet Pivot table2
A1: Row Labels | B1: Sum of Quantity
A2: Jan | B2: 8
A3: Feb | B3: 17
A4: Mar | B4: 24
A5: Apr | B5: 23
A6: May | B6: 14
A7: Jun | B7: 20
A8: Jul | B8: 40
A9: Aug | B9: 19
A10: Sep | B10: 46
A11: Oct | B11: 15
A12: Nov | B12: 18
A13: Dec | B13: 26
A14: Grand Total | B14: 270
